{"stats":{"minecraft:mined":{"minecraft:grass":6,"minecraft:grass_block":1,"minecraft:oak_leaves":3},"minecraft:killed_by":{"minecraft:spider":1},"minecraft:killed":{"minecraft:skeleton":2,"minecraft:wolf":1,"minecraft:zombie":8,"minecraft:witch":1,"minecraft:spider":2},"minecraft:dropped":{"minecraft:iron_ingot":1,"minecraft:wheat_seeds":1,"minecraft:bowl":3,"minecraft:rotten_flesh":3,"farmersdelight:straw":1,"farmersdelight:roast_chicken":1,"minecraft:acacia_log":1,"minecraft:grass_block":2},"minecraft:custom":{"minecraft:time_since_rest":5015,"minecraft:sprint_one_cm":78542,"minecraft:walk_one_cm":45391,"minecraft:damage_taken":911,"minecraft:damage_absorbed":40,"minecraft:mob_kills":14,"minecraft:drop":11,"minecraft:damage_dealt":3021,"minecraft:fly_one_cm":517485,"minecraft:deaths":1,"minecraft:crouch_one_cm":856,"minecraft:play_time":51811,"minecraft:sneak_time":868,"minecraft:walk_under_water_one_cm":7833,"minecraft:aviate_one_cm":416150,"minecraft:jump":863,"minecraft:leave_game":6,"minecraft:walk_on_water_one_cm":5066,"minecraft:time_since_death":4992,"minecraft:climb_one_cm":3008,"minecraft:total_world_time":51811,"minecraft:damage_resisted":8,"minecraft:fall_one_cm":10575},"minecraft:used":{"farmersdelight:roast_chicken_block":3,"mynethersdelight:roast_stuffed_hoglin":1,"minecraft:firework_rocket":16,"farmersdelight:netherite_knife":41,"friendsandfoes:wildfire_spawn_egg":1,"minecraft:grass_block":3,"minecraft:decorated_pot":1,"mynethersdelight:plate_of_stuffed_hoglin_snout":1,"outer_end:glowing_ancient_ice":1,"ends_delight:chorus_flower_tea":1,"minecraft:rotten_flesh":1,"minecraft:golden_apple":2,"ends_delight:steamed_dragon_egg":1,"minecraft:diamond_sword":7,"farmersdelight:onion":1,"mynethersdelight:roast_ear":1,"minecraft:pumpkin_pie":4,"minecraft:cooked_beef":8,"minecraft:potato":12,"minecraft:enchanted_golden_apple":2,"farmersdelight:roast_chicken":1},"minecraft:picked_up":{"minecraft:stick":2,"ecologics:coconut_slice":2,"minecraft:bowl":2,"minecraft:acacia_log":1,"minecraft:grass_block":1,"minecraft:string":3,"minecraft:dirt":1,"minecraft:arrow":4,"minecraft:bone":4,"minecraft:rotten_flesh":9,"farmersdelight:roast_chicken":1,"minecraft:wheat_seeds":1,"minecraft:iron_ingot":1,"farmersdelight:straw":1,"minecraft:oak_sapling":1,"mynethersdelight:roast_ear":2,"minecraft:egg":1}},"DataVersion":3465}